smplcli/__init__.py
smplcli/tokens.py
smplcli-0.1.0.dist-info/LICENSE
smplcli-0.1.0.dist-info/METADATA
smplcli-0.1.0.dist-info/WHEEL
smplcli-0.1.0.dist-info/RECORD
